ChangeLog.rst
LICENSE
MANIFEST.in
README.rst
setup.cfg
setup.py
reclass/__init__.py
reclass/cli.py
reclass/config.py
reclass/constants.py
reclass/core.py
reclass/defaults.py
reclass/errors.py
reclass/version.py
reclass.egg-info/PKG-INFO
reclass.egg-info/SOURCES.txt
reclass.egg-info/dependency_links.txt
reclass.egg-info/entry_points.txt
reclass.egg-info/requires.txt
reclass.egg-info/top_level.txt
reclass/adapters/__init__.py
reclass/adapters/ansible.py
reclass/adapters/salt.py
reclass/datatypes/__init__.py
reclass/datatypes/applications.py
reclass/datatypes/classes.py
reclass/datatypes/entity.py
reclass/datatypes/parameters.py
reclass/output/__init__.py
reclass/output/json_outputter.py
reclass/output/yaml_outputter.py
reclass/storage/__init__.py
reclass/storage/loader.py
reclass/storage/memcache_proxy.py
reclass/storage/yaml_fs/__init__.py
reclass/storage/yaml_fs/directory.py
reclass/storage/yaml_fs/yamlfile.py
reclass/utils/__init__.py
reclass/utils/dictpath.py
reclass/utils/refvalue.py